[
  {
    "startStationName": "CHEDDIIKULAM",
    "arrivalTime": "18:01:00",
    "depatureTime": "18:02:00",
    "trainFrequncy": "DAILY",
    "trainName": "5445",
    "finalStationName": "TALAIMANNAR PIER",
    "arrivalTimeFinalStation": "19:25:00",
    "endStationName": "TALAIMANNAR PIER",
    "arrivalTimeEndStation": "19:25:00",
    "classList": [
      {
        "className": "2nd Class",
        "price": "400.00"
      },
      {
        "className": "3rd Class",
        "price": "200.00"
      }
    ],
    "trainNo": "5445"
  }
]