[
  {
    "startStationName": "KALKUDAH",
    "arrivalTime": "11:48:00",
    "depatureTime": "11:49:00",
    "trainFrequncy": "DAILY",
    "trainName": "",
    "finalStationName": "MAHO",
    "arrivalTimeFinalStation": "18:28:00",
    "endStationName": "RANAMUGGAMUWA",
    "arrivalTimeEndStation": "18:04:00",
    "classList": [
      {
        "className": "2nd Class",
        "price": "600.00"
      },
      {
        "className": "3rd Class",
        "price": "300.00"
      }
    ],
    "trainNo": "6891"
  }
]