[
  {
    "startStationName": "VEYANGODA",
    "arrivalTime": "14:06:00",
    "depatureTime": "14:08:00",
    "trainFrequncy": "DAILY",
    "trainName": "Rajarata Rejini",
    "finalStationName": "ANURADHAPURA",
    "arrivalTimeFinalStation": "18:22:00",
    "endStationName": "ABANPOLA",
    "arrivalTimeEndStation": "16:54:00",
    "classList": [
      {
        "className": "2nd Class",
        "price": "450.00"
      },
      {
        "className": "3rd Class",
        "price": "240.00"
      }
    ],
    "trainNo": "4085"
  }
]