[
  {
    "startStationName": "ERAVUR",
    "arrivalTime": "11:19:00",
    "depatureTime": "11:20:00",
    "trainFrequncy": "DAILY",
    "trainName": "",
    "finalStationName": "MAHO",
    "arrivalTimeFinalStation": "18:28:00",
    "endStationName": "GALLELLA",
    "arrivalTimeEndStation": "13:48:00",
    "classList": [
      {
        "className": "2nd Class",
        "price": "350.00"
      },
      {
        "className": "3rd Class",
        "price": "180.00"
      }
    ],
    "trainNo": "6891"
  }
]