[
  {
    "startStationName": "KOSGODA",
    "arrivalTime": "16:01:00",
    "depatureTime": "16:02:00",
    "trainFrequncy": "DAILY",
    "trainName": "",
    "finalStationName": "BELIATHTHA",
    "arrivalTimeFinalStation": "18:42:00",
    "endStationName": "MATARA",
    "arrivalTimeEndStation": "18:06:00",
    "classList": [
      {
        "className": "2nd Class",
        "price": "400.00"
      },
      {
        "className": "3rd Class",
        "price": "200.00"
      }
    ],
    "trainNo": "8750"
  },
  {
    "startStationName": "KOSGODA",
    "arrivalTime": "16:57:00",
    "depatureTime": "16:58:00",
    "trainFrequncy": "DAILY",
    "trainName": "RUHUNU KUMARI",
    "finalStationName": "MATARA",
    "arrivalTimeFinalStation": "18:21:00",
    "endStationName": "MATARA",
    "arrivalTimeEndStation": "18:21:00",
    "classList": [
      {
        "className": "2nd Class",
        "price": "400.00"
      },
      {
        "className": "3rd Class",
        "price": "200.00"
      }
    ],
    "trainNo": "8058"
  }
]