[
  {
    "startStationName": "IHALAWATAWALA",
    "arrivalTime": "06:30:00",
    "depatureTime": "06:31:00",
    "trainFrequncy": "DAILY",
    "trainName": "",
    "finalStationName": "BADULLA",
    "arrivalTimeFinalStation": "14:28:00",
    "endStationName": "ROSELLA",
    "arrivalTimeEndStation": "06:42:00",
    "classList": [
      {
        "className": "1st Class"
      },
      {
        "className": "2nd Class",
        "price": "50.00"
      },
      {
        "className": "3rd Class",
        "price": "20.00"
      }
    ],
    "trainNo": "1126"
  },
  {
    "startStationName": "IHALAWATAWALA",
    "arrivalTime": "11:15:00",
    "depatureTime": "11:16:00",
    "trainFrequncy": "DAILY",
    "trainName": "Podi  Menike",
    "finalStationName": "BADULLA",
    "arrivalTimeFinalStation": "16:26:00",
    "endStationName": "ROSELLA",
    "arrivalTimeEndStation": "11:24:00",
    "classList": [
      {
        "className": "1st Class"
      },
      {
        "className": "2nd Class",
        "price": "50.00"
      },
      {
        "className": "3rd Class",
        "price": "20.00"
      }
    ],
    "trainNo": "1005"
  },
  {
    "startStationName": "IHALAWATAWALA",
    "arrivalTime": "12:54:00",
    "depatureTime": "12:55:00",
    "trainFrequncy": "DAILY",
    "trainName": "Udarata Menike",
    "finalStationName": "BADULLA",
    "arrivalTimeFinalStation": "17:50:00",
    "endStationName": "ROSELLA",
    "arrivalTimeEndStation": "13:04:00",
    "classList": [
      {
        "className": "1st Class"
      },
      {
        "className": "2nd Class",
        "price": "50.00"
      },
      {
        "className": "3rd Class",
        "price": "20.00"
      }
    ],
    "trainNo": "1015"
  },
  {
    "startStationName": "IHALAWATAWALA",
    "arrivalTime": "15:53:00",
    "depatureTime": "15:54:00",
    "trainFrequncy": "DAILY",
    "trainName": "",
    "finalStationName": "NANUOYA",
    "arrivalTimeFinalStation": "17:59:00",
    "endStationName": "ROSELLA",
    "arrivalTimeEndStation": "16:05:00",
    "classList": [
      {
        "className": "3rd Class",
        "price": "20.00"
      }
    ],
    "trainNo": "1159"
  },
  {
    "startStationName": "IHALAWATAWALA",
    "arrivalTime": "19:36:00",
    "depatureTime": "19:37:00",
    "trainFrequncy": "DAILY",
    "trainName": "",
    "finalStationName": "NANUOYA",
    "arrivalTimeFinalStation": "21:19:00",
    "endStationName": "ROSELLA",
    "arrivalTimeEndStation": "19:46:00",
    "classList": [
      {
        "className": "2nd Class",
        "price": "50.00"
      },
      {
        "className": "3rd Class",
        "price": "20.00"
      }
    ],
    "trainNo": "1023"
  }
]