[
  {
    "startStationName": "PALLE TALAVINNA",
    "arrivalTime": "05:01:00",
    "depatureTime": "05:02:00",
    "trainFrequncy": "DAILY",
    "trainName": "",
    "finalStationName": "MATALE",
    "arrivalTimeFinalStation": "06:06:00",
    "endStationName": "YATIRAWANA",
    "arrivalTimeEndStation": "05:14:00",
    "classList": [
      {
        "className": "2nd Class",
        "price": "50.00"
      },
      {
        "className": "3rd Class",
        "price": "20.00"
      }
    ],
    "trainNo": "2231"
  },
  {
    "startStationName": "PALLE TALAVINNA",
    "arrivalTime": "07:26:00",
    "depatureTime": "07:27:00",
    "trainFrequncy": "DAILY",
    "trainName": "",
    "finalStationName": "MATALE",
    "arrivalTimeFinalStation": "08:21:00",
    "endStationName": "YATIRAWANA",
    "arrivalTimeEndStation": "07:39:00",
    "classList": [
      {
        "className": "3rd Class",
        "price": "20.00"
      }
    ],
    "trainNo": "2236"
  },
  {
    "startStationName": "PALLE TALAVINNA",
    "arrivalTime": "08:44:00",
    "depatureTime": "08:45:00",
    "trainFrequncy": "DAILY",
    "trainName": "-",
    "finalStationName": "WATTEGAMA",
    "arrivalTimeFinalStation": "09:01:00",
    "endStationName": "YATIRAWANA",
    "arrivalTimeEndStation": "08:57:00",
    "classList": [
      {
        "className": "3rd Class",
        "price": "20.00"
      }
    ],
    "trainNo": "1139"
  },
  {
    "startStationName": "PALLE TALAVINNA",
    "arrivalTime": "10:47:00",
    "depatureTime": "10:48:00",
    "trainFrequncy": "DAILY",
    "trainName": "",
    "finalStationName": "MATALE",
    "arrivalTimeFinalStation": "11:43:00",
    "endStationName": "YATIRAWANA",
    "arrivalTimeEndStation": "11:00:00",
    "classList": [
      {
        "className": "3rd Class",
        "price": "20.00"
      }
    ],
    "trainNo": "2237"
  },
  {
    "startStationName": "PALLE TALAVINNA",
    "arrivalTime": "14:21:00",
    "depatureTime": "14:22:00",
    "trainFrequncy": "DAILY",
    "trainName": "",
    "finalStationName": "MATALE",
    "arrivalTimeFinalStation": "15:16:00",
    "endStationName": "YATIRAWANA",
    "arrivalTimeEndStation": "14:34:00",
    "classList": [
      {
        "className": "3rd Class",
        "price": "20.00"
      }
    ],
    "trainNo": "2019"
  },
  {
    "startStationName": "PALLE TALAVINNA",
    "arrivalTime": "14:25:00",
    "depatureTime": "14:26:00",
    "trainFrequncy": "NOT ON  SATURDAY & SUNDAY",
    "trainName": "",
    "finalStationName": "MATALE",
    "arrivalTimeFinalStation": "15:23:00",
    "endStationName": "YATIRAWANA",
    "arrivalTimeEndStation": "14:38:00",
    "classList": [
      {
        "className": "2nd Class",
        "price": "50.00"
      },
      {
        "className": "3rd Class",
        "price": "20.00"
      }
    ],
    "trainNo": "1019"
  },
  {
    "startStationName": "PALLE TALAVINNA",
    "arrivalTime": "17:51:00",
    "depatureTime": "17:52:00",
    "trainFrequncy": "DAILY",
    "trainName": "",
    "finalStationName": "MATALE",
    "arrivalTimeFinalStation": "18:49:00",
    "endStationName": "YATIRAWANA",
    "arrivalTimeEndStation": "18:04:00",
    "classList": [
      {
        "className": "3rd Class",
        "price": "20.00"
      }
    ],
    "trainNo": "2243"
  },
  {
    "startStationName": "PALLE TALAVINNA",
    "arrivalTime": "19:21:00",
    "depatureTime": "19:22:00",
    "trainFrequncy": "DAILY",
    "trainName": "",
    "finalStationName": "MATALE",
    "arrivalTimeFinalStation": "20:22:00",
    "endStationName": "YATIRAWANA",
    "arrivalTimeEndStation": "19:34:00",
    "classList": [
      {
        "className": "3rd Class",
        "price": "20.00"
      }
    ],
    "trainNo": "2244"
  }
]